mlcvzoo_mmrotate/__init__.py
mlcvzoo_mmrotate/py.typed
mlcvzoo_mmrotate/rotated_object_detection_model.py
mlcvzoo_mmrotate-0.1.0.dist-info/LICENSE
mlcvzoo_mmrotate-0.1.0.dist-info/METADATA
mlcvzoo_mmrotate-0.1.0.dist-info/WHEEL
mlcvzoo_mmrotate-0.1.0.dist-info/RECORD
