Metadata-Version: 2.1
Name: mlcvzoo-mmrotate
Version: 0.1.0
Summary: MLCVZoo MMRotate Package
Home-page: https://git.openlogisticsfoundation.org/silicon-economy/base/ml-toolbox/mlcvzoo-mmrotate
License: Open Logistics Foundation License 1.3
Author: Maximilian Otten
Author-email: maximilian.otten@iml.fraunhofer.de
Requires-Python: >=3.8,<4.0
Classifier: Development Status :: 5 - Production/Stable
Classifier: Intended Audience :: Developers
Classifier: License :: Other/Proprietary License
Classifier: Natural Language :: English
Classifier: Programming Language :: Python :: 3
Classifier: Programming Language :: Python :: 3.8
Classifier: Programming Language :: Python :: 3.9
Classifier: Programming Language :: Python :: 3.10
Classifier: Programming Language :: Python :: 3.11
Requires-Dist: attrs (>=20)
Requires-Dist: mlcvzoo_base (>=5,<6)
Requires-Dist: mlcvzoo_mmdetection (>=6,<7)
Requires-Dist: mmcv (>=2,<2.1.0)
Requires-Dist: mmdet (>=3,<3.1)
Requires-Dist: mmengine (>=0.7,<0.8)
Requires-Dist: mmrotate (==1.0.0rc1)
Requires-Dist: nptyping (>=2.0)
Requires-Dist: numpy (>=1.19.2,!=1.19.5)
Requires-Dist: opencv-contrib-python (>=4.5,!=4.5.5.64,!=4.6.0.66)
Requires-Dist: opencv-python (>=4.5,!=4.5.5.64,!=4.6.0.66)
Requires-Dist: pycocotools (>=2.0.2) ; platform_machine == "x86_64"
Requires-Dist: related-mltoolbox (>=1,<2)
Requires-Dist: torch (>=1.9,!=2.0.1,<2.1)
Requires-Dist: torchvision (>=0.10)
Requires-Dist: yaml-config-builder (>=8,<9)
Requires-Dist: yapf (!=0.40.2)
Project-URL: Documentation, https://git.openlogisticsfoundation.org/silicon-economy/base/ml-toolbox/mlcvzoo-mmrotate/-/blob/main/documentation/index.adoc
Project-URL: Repository, https://git.openlogisticsfoundation.org/silicon-economy/base/ml-toolbox/mlcvzoo-mmrotate
